ValueCalculator/VC.py
ValueCalculator/__init__.py
ValueCalculator-1.0.0.dist-info/LICENSE
ValueCalculator-1.0.0.dist-info/METADATA
ValueCalculator-1.0.0.dist-info/WHEEL
ValueCalculator-1.0.0.dist-info/top_level.txt
ValueCalculator-1.0.0.dist-info/RECORD
