Metadata-Version: 2.1
Name: ValueCalculator
Version: 1.0.0
Summary: Used to calculate the rise and fall of stocks
Home-page: https://github.com/V-Calculator/ValueCalculator
Author: LJY
Author-email: ljy123ljy123@dingtalk.com
License: UNKNOWN
Platform: UNKNOWN
Classifier: Programming Language :: Python :: 3.8
Classifier: License :: OSI Approved :: MIT License
Classifier: Operating System :: OS Independent
Requires-Python: >=3.8
Provides-Extra: valuecalculator
Requires-Dist: python ; extra == 'valuecalculator'
